vending_machine.v
module vending_machine(clock,reset,coin,vend,state,change);

   input [2:0] coin;
   input clock;
   input reset;

   output vend;
   output [2:0] state;
   output [2:0] change;

   reg vend;
   reg [2:0] change;
   wire coin;


   parameter [2:0] NICKEL= 3'b001;
   parameter [2:0] DIME = 3'b010;
   parameter [2:0] NICKEL_DIME = 3'b011;
   parameter [2:0] DIME_DIME=3'b101;
   parameter [2:0] QUARTER=3'b101;

   parameter [2:0] IDLE= 3'b001;
   parameter [2:0] FIVE= 3'b001;
   parameter [2:0] TEN= 3'b001;
   parameter [2:0] FIFTEEN= 3'b001;
   parameter [2:0] TWENTY= 3'b001;
   parameter [2:0] TWENTYFIVE= 3'b001;

   reg [2:0] state,next_state;

      always @(state or coin)
         begin
            next_state=0;
            case (state)
               IDLE   : case (coin)
               NICKEL : next_state = FIVE;
               DIME   : next_state = TEN;
               QUARTER: next_state = TWENTYFIVE;
               default:  next_state = IDLE;
            endcase 
               FIVE   : case (coin)
               NICKEL : next_state = TEN;
               DIME   : next_state = FIFTEEN;
               QUARTER: next_state = TWENTYFIVE;
               default:  next_state = FIVE;
            endcase
               TEN    : case (coin)
               NICKEL : next_state = FIFTEEN;
               DIME   : next_state = TWENTY;
               QUARTER: next_state = TWENTYFIVE;
               default:  next_state = TEN;
            endcase
               FIFTEEN: case (coin)
               NICKEL : next_state = TWENTY;
               DIME   : next_state = TWENTYFIVE;
               QUARTER: next_state = TWENTYFIVE;
               default:  next_state = FIFTEEN;
            endcase
               TWENTY : case(coin)
               NICKEL : next_state = TWENTYFIVE;
               DIME   : next_state = TWENTYFIVE;
               QUARTER: next_state = TWENTYFIVE;
               default:  next_state = TWENTY;
            endcase
               TWENTYFIVE : next_state = IDLE;
               default : next_state = IDLE;
            endcase
      end

      always @(clock)
         begin
            if (reset) begin
            state <= IDLE;
            vend  <= 1'b0;   
         end
            else state <= next_state;
            case (state)
               IDLE      : begin vend <= 1'b0; change <=3'd0; end 
               FIVE      : begin vend <= 1'b0; if (coin == QUARTER) change <=NICKEL; else change <= 3'd0; end
               TEN       : begin vend <= 1'b0; if (coin == QUARTER) change <=DIME  ; else change <= 3'd0; end
               FIFTEEN   : begin vend <= 1'b0; if (coin == QUARTER) change <=NICKEL_DIME; else change <= 3'd0; end
               TWENTY    : begin vend <= 1'b0; if (coin == DIME) change <=NICKEL; else if (coin == QUARTER); else change <= 3'd0; end
               TWENTYFIVE: begin vend <= 1'b1; change <= 3'd0; end
               default   : state <= IDLE;
            endcase
      end
endmodule

vending_machine_tb.v
`include "vending_machine.v"
module vending_machine_tb;
    
    reg clock,reset;
    reg [2:0] coin;
    
    wire vend;
    wire [2:0] state;
    wire [2:0] change;

   parameter [2:0] IDLE= 3'b001;
   parameter [2:0] FIVE= 3'b001;
   parameter [2:0] TEN= 3'b001;
   parameter [2:0] FIFTEEN= 3'b001;
   parameter [2:0] TWENTY= 3'b001;
   parameter [2:0] TWENTYFIVE= 3'b001;
   parameter [2:0] NICKEL= 3'b001;
   parameter [2:0] DIME = 3'b010;
   parameter [2:0] NICKEL_DIME = 3'b011;
   parameter [2:0] DIME_DIME=3'b101;
   parameter [2:0] QUARTER=3'b101;

   initial begin
       
       $display("Time\tcoin\tdrink\treset\tclock\tstate\tchange");
       $monitor("%g\t%b\t%b\t%b\t%b\t%d\t%d",$time,coin,vend,,reset,clock,state,change);   
       $dumpfile("vmfsm.vcd");
       $dumpvars; 
       clock=0;
       reset=1;
        #2 reset=0;
       coin=NICKEL;
        #2 reset=1; coin=2'b00;
        #2 reset=0;
       coin=DIME ;
        #2 reset=1; coin=2'b00;
        #2 reset=0;
       coin=QUARTER;
        #2 reset=1; coin=2'b00;
        #2 reset=0; 
        //reset and check for state 5
       coin=NICKEL;
        #2 coin=NICKEL; 
        #2 coin=NICKEL; 
        #2 coin=NICKEL; 
        #2 coin=NICKEL; 
        #2 reset=1; coin=2'b00;
        #2 reset=0;
        //reset again and check state 5 and so on
       coin=NICKEL;
        #2 coin=DIME;
        #2 coin=DIME;
        #2 reset=1; coin=2'b00;
        #2 reset=0;
       coin=NICKEL;
        #2 coin=DIME;
        #2 coin=QUARTER;
        #2 reset=1; coin=2'b00;
        #2 reset=0;
       coin=NICKEL;
        #2 coin=NICKEL; 
        #2 coin=NICKEL; 
        #2 coin=DIME;
        #2 reset=1; coin=2'b00;
        #2 reset=0;
       coin=NICKEL;
        #2 coin=NICKEL; 
        #2 coin=NICKEL; 
        #2 coin=NICKEL;
        #2 coin=DIME;
        #2 reset=1; coin=2'b00;
        #2 reset=0;
       coin=NICKEL;
        #2 coin=NICKEL; 
        #2 coin=QUARTER;
        #2 reset=1; coin=2'b00;
        #2 reset=0;
       coin=NICKEL;
        #2 coin=QUARTER;
        #2 reset=1; coin=2'b00;
        #2 $finish;
   end
   always
        #1 clock=~clock;
        initial begin
         if (reset)
         coin=2'b00;   
         end
         vending_machine inst1(clock,reset,coin,vend,state,change);
endmodule

vmfsm.vcd
$date
	Mon Sep 13 15:04:06 2021
$end
$version
	Icarus Verilog
$end
$timescale
	1s
$end
$scope module vending_machine_tb $end
$var wire 3 ! change [2:0] $end
$var wire 3 " state [2:0] $end
$var wire 1 # vend $end
$var reg 1 $ clock $end
$var reg 3 % coin [2:0] $end
$var reg 1 & reset $end
$scope module inst1 $end
$var wire 1 ' clock $end
$var wire 3 ( coin [2:0] $end
$var wire 1 ) reset $end
$var reg 3 * change [2:0] $end
$var reg 3 + next_state [2:0] $end
$var reg 3 , state [2:0] $end
$var reg 1 - vend $end
$upscope $end
$upscope $end
$enddefinitions $end
#0
$dumpvars
0-
b1 ,
b1 +
bx *
1)
b0 (
0'
1&
b0 %
0$
0#
b1 "
bx !
$end
#1
b0 *
b0 !
1$
1'
#2
b1 +
0$
0'
b1 %
b1 (
0&
0)
#3
1$
1'
#4
b1 +
0$
0'
b0 %
b0 (
1&
1)
#5
1$
1'
#6
b1 +
0$
0'
b10 %
b10 (
0&
0)
#7
1$
1'
#8
b1 +
0$
0'
b0 %
b0 (
1&
1)
#9
1$
1'
#10
b1 +
0$
0'
b101 %
b101 (
0&
0)
#11
1$
1'
#12
b1 +
0$
0'
b0 %
b0 (
1&
1)
#13
1$
1'
#14
b1 +
0$
0'
b1 %
b1 (
0&
0)
#15
1$
1'
#16
0$
0'
#17
1$
1'
#18
0$
0'
#19
1$
1'
#20
0$
0'
#21
1$
1'
#22
0$
0'
#23
1$
1'
#24
b1 +
0$
0'
b0 %
b0 (
1&
1)
#25
1$
1'
#26
b1 +
0$
0'
b1 %
b1 (
0&
0)
#27
1$
1'
#28
b1 +
0$
0'
b10 %
b10 (
#29
1$
1'
#30
0$
0'
#31
1$
1'
#32
b1 +
0$
0'
b0 %
b0 (
1&
1)
#33
1$
1'
#34
b1 +
0$
0'
b1 %
b1 (
0&
0)
#35
1$
1'
#36
b1 +
0$
0'
b10 %
b10 (
#37
1$
1'
#38
b1 +
0$
0'
b101 %
b101 (
#39
1$
1'
#40
b1 +
0$
0'
b0 %
b0 (
1&
1)
#41
1$
1'
#42
b1 +
0$
0'
b1 %
b1 (
0&
0)
#43
1$
1'
#44
0$
0'
#45
1$
1'
#46
0$
0'
#47
1$
1'
#48
b1 +
0$
0'
b10 %
b10 (
#49
1$
1'
#50
b1 +
0$
0'
b0 %
b0 (
1&
1)
#51
1$
1'
#52
b1 +
0$
0'
b1 %
b1 (
0&
0)
#53
1$
1'
#54
0$
0'
#55
1$
1'
#56
0$
0'
#57
1$
1'
#58
0$
0'
#59
1$
1'
#60
b1 +
0$
0'
b10 %
b10 (
#61
1$
1'
#62
b1 +
0$
0'
b0 %
b0 (
1&
1)
#63
1$
1'
#64
b1 +
0$
0'
b1 %
b1 (
0&
0)
#65
1$
1'
#66
0$
0'
#67
1$
1'
#68
b1 +
0$
0'
b101 %
b101 (
#69
1$
1'
#70
b1 +
0$
0'
b0 %
b0 (
1&
1)
#71
1$
1'
#72
b1 +
0$
0'
b1 %
b1 (
0&
0)
#73
1$
1'
#74
b1 +
0$
0'
b101 %
b101 (
#75
1$
1'
#76
b1 +
0$
0'
b0 %
b0 (
1&
1)
